j2tools/__init__.py
j2tools/elapsed.py
j2tools/plural.py
j2tools/t.py
j2tools/uchar.py
j2tools/yamlloader.py
j2tools-2019.3.dist-info/LICENSE
j2tools-2019.3.dist-info/METADATA
j2tools-2019.3.dist-info/WHEEL
j2tools-2019.3.dist-info/top_level.txt
j2tools-2019.3.dist-info/RECORD
